scopeagent/__init__.py
scopeagent/compat.py
scopeagent/agent/__init__.py
scopeagent/agent/agent.py
scopeagent/agent/ci.py
scopeagent/agent/config.py
scopeagent/agent/git.py
scopeagent/agent/metadata.py
scopeagent/agent/modules.py
scopeagent/agent/utils.py
scopeagent/cli/__init__.py
scopeagent/cli/__main__.py
scopeagent/cli/main.py
scopeagent/cli/wrapper/__init__.py
scopeagent/cli/wrapper/sitecustomize.py
scopeagent/formatters/__init__.py
scopeagent/formatters/base.py
scopeagent/formatters/coverage.py
scopeagent/formatters/dict.py
scopeagent/instrumentation/__init__.py
scopeagent/instrumentation/app_celery.py
scopeagent/instrumentation/client_kombu.py
scopeagent/instrumentation/client_requests.py
scopeagent/instrumentation/client_urllib_request.py
scopeagent/instrumentation/db_psycopg2.py
scopeagent/instrumentation/http_utils.py
scopeagent/instrumentation/logging_logging.py
scopeagent/instrumentation/server_django.py
scopeagent/instrumentation/server_flask.py
scopeagent/instrumentation/server_uvicorn.py
scopeagent/instrumentation/stacktrace.py
scopeagent/instrumentation/testing_coverage.py
scopeagent/instrumentation/testing_pytest.py
scopeagent/instrumentation/testing_pytest_benchmark.py
scopeagent/instrumentation/testing_unittest.py
scopeagent/instrumentation/sql/__init__.py
scopeagent/instrumentation/sql/_dbapi2.py
scopeagent/instrumentation/sql/local_span.py
scopeagent/instrumentation/sql/psycopg2.py
scopeagent/instrumentation/wrappers/__init__.py
scopeagent/instrumentation/wrappers/asgi.py
scopeagent/instrumentation/wrappers/wsgi.py
scopeagent/recorders/__init__.py
scopeagent/recorders/asyncrecorder.py
scopeagent/recorders/http.py
scopeagent/recorders/utils.py
scopeagent/tracer/__init__.py
scopeagent/tracer/context.py
scopeagent/tracer/exception.py
scopeagent/tracer/propagator.py
scopeagent/tracer/recorder.py
scopeagent/tracer/span.py
scopeagent/tracer/tags.py
scopeagent/tracer/text_propagator.py
scopeagent/tracer/tracer.py
scopeagent/tracer/util.py
scopeagent-0.5.0.dist-info/LICENSE
scopeagent-0.5.0.dist-info/METADATA
scopeagent-0.5.0.dist-info/NOTICE
scopeagent-0.5.0.dist-info/WHEEL
scopeagent-0.5.0.dist-info/entry_points.txt
scopeagent-0.5.0.dist-info/top_level.txt
scopeagent-0.5.0.dist-info/RECORD
